{
  "id": 9563984757017,
  "title": "Fisker Ocean Bakre Skvettlapper v2",
  "handle": "fisker-ocean-bakre-skvettlapper-v2",
  "status": "active",
  "product_type": "Tilbehør til kjøretøy",
  "vendor": "PROTONORD",
  "tags": "Elbil, Elektrisk kjøretøy, FISKER, Fisker Ocean, Mudflaps, Skvettlapper",
  "options": [
    {
      "id": 12023837950233,
      "product_id": 9563984757017,
      "name": "Modell",
      "position": 1,
      "values": [
        "Skvettlapp BR u/farge",
        "Skvettlapp BL u/farge",
        "Skvettlapp BR m/farge",
        "Skvettlapp BL m/farge",
        "Farge innlegg BR",
        "Farge innlegg BL"
      ]
    },
    {
      "id": 12023837983001,
      "product_id": 9563984757017,
      "name": "Farge",
      "position": 2,
      "values": [
        "Sort",
        "Oransje",
        "Carbonfiber purpur",
        "Carbonfiber sort"
      ]
    }
  ],
  "variants": [
    {
      "id": 49211002159385,
      "title": "Skvettlapp BR u/farge / Sort",
      "sku": "PFI-SS-D-P-0195-S",
      "price": "399.00",
      "compare_at_price": null,
      "barcode": "",
      "weight": 300.0,
      "weight_unit": "g",
      "inventory_policy": "deny",
      "taxable": true,
      "requires_shipping": true
    },
    {
      "id": 49211002192153,
      "title": "Skvettlapp BL u/farge / Sort",
      "sku": "PFI-SS-D-P-0196-S",
      "price": "399.00",
      "compare_at_price": null,
      "barcode": "",
      "weight": 300.0,
      "weight_unit": "g",
      "inventory_policy": "deny",
      "taxable": true,
      "requires_shipping": true
    },
    {
      "id": 49211001897241,
      "title": "Skvettlapp BR m/farge / Oransje",
      "sku": "PFI-SO-D-P-0197-S",
      "price": "495.00",
      "compare_at_price": null,
      "barcode": "",
      "weight": 300.0,
      "weight_unit": "g",
      "inventory_policy": "deny",
      "taxable": true,
      "requires_shipping": true
    },
    {
      "id": 49261352059161,
      "title": "Skvettlapp BR m/farge / Carbonfiber purpur",
      "sku": "PFI-SS-D-P-0195-S-3",
      "price": "599.00",
      "compare_at_price": null,
      "barcode": null,
      "weight": 300.0,
      "weight_unit": "g",
      "inventory_policy": "deny",
      "taxable": true,
      "requires_shipping": true
    },
    {
      "id": 49211001930009,
      "title": "Skvettlapp BR m/farge / Carbonfiber sort",
      "sku": "PFI-SR-D-P-0198-S",
      "price": "599.00",
      "compare_at_price": null,
      "barcode": "",
      "weight": 300.0,
      "weight_unit": "g",
      "inventory_policy": "deny",
      "taxable": true,
      "requires_shipping": true
    },
    {
      "id": 49211001962777,
      "title": "Skvettlapp BL m/farge / Oransje",
      "sku": "PFI-SO-D-P-0199-S",
      "price": "495.00",
      "compare_at_price": null,
      "barcode": "",
      "weight": 300.0,
      "weight_unit": "g",
      "inventory_policy": "deny",
      "taxable": true,
      "requires_shipping": true
    },
    {
      "id": 49261352091929,
      "title": "Skvettlapp BL m/farge / Carbonfiber purpur",
      "sku": "PFI-SS-D-P-0195-S-4",
      "price": "599.00",
      "compare_at_price": null,
      "barcode": null,
      "weight": 300.0,
      "weight_unit": "g",
      "inventory_policy": "deny",
      "taxable": true,
      "requires_shipping": true
    },
    {
      "id": 49211001995545,
      "title": "Skvettlapp BL m/farge / Carbonfiber sort",
      "sku": "PFI-SR-D-P-0200-S",
      "price": "599.00",
      "compare_at_price": null,
      "barcode": "",
      "weight": 300.0,
      "weight_unit": "g",
      "inventory_policy": "deny",
      "taxable": true,
      "requires_shipping": true
    },
    {
      "id": 49211002028313,
      "title": "Farge innlegg BR / Oransje",
      "sku": "PFI-FO-D-P-0201-S",
      "price": "120.00",
      "compare_at_price": null,
      "barcode": "",
      "weight": 300.0,
      "weight_unit": "g",
      "inventory_policy": "deny",
      "taxable": true,
      "requires_shipping": true
    },
    {
      "id": 49261352124697,
      "title": "Farge innlegg BR / Carbonfiber purpur",
      "sku": "PFI-SS-D-P-0195-S-5",
      "price": "220.00",
      "compare_at_price": null,
      "barcode": null,
      "weight": 300.0,
      "weight_unit": "g",
      "inventory_policy": "deny",
      "taxable": true,
      "requires_shipping": true
    },
    {
      "id": 49211002061081,
      "title": "Farge innlegg BR / Carbonfiber sort",
      "sku": "PFI-FR-D-P-0202-S",
      "price": "220.00",
      "compare_at_price": null,
      "barcode": "",
      "weight": 300.0,
      "weight_unit": "g",
      "inventory_policy": "deny",
      "taxable": true,
      "requires_shipping": true
    },
    {
      "id": 49211002093849,
      "title": "Farge innlegg BL / Oransje",
      "sku": "PFI-FO-D-P-0203-S",
      "price": "120.00",
      "compare_at_price": null,
      "barcode": "",
      "weight": 300.0,
      "weight_unit": "g",
      "inventory_policy": "deny",
      "taxable": true,
      "requires_shipping": true
    },
    {
      "id": 49261352157465,
      "title": "Farge innlegg BL / Carbonfiber purpur",
      "sku": "PFI-SS-D-P-0195-S-6",
      "price": "220.00",
      "compare_at_price": null,
      "barcode": null,
      "weight": 300.0,
      "weight_unit": "g",
      "inventory_policy": "deny",
      "taxable": true,
      "requires_shipping": true
    },
    {
      "id": 49211002126617,
      "title": "Farge innlegg BL / Carbonfiber sort",
      "sku": "PFI-FR-D-P-0204-S",
      "price": "220.00",
      "compare_at_price": null,
      "barcode": "",
      "weight": 300.0,
      "weight_unit": "g",
      "inventory_policy": "deny",
      "taxable": true,
      "requires_shipping": true
    }
  ],
  "body_html": "<p><span style=\"text-decoration: underline;\"><em><strong><br>For EU bruk <a href=\"https://www.protonord.eu\" rel=\"noopener noreferrer\" target=\"_blank\">https://www.protonord.eu </a></strong></em></span></p>\n<p>festes med en original skruefeste i hjulbuen.</p>\n<p>Selve skvettlapp venstre/høyre kommer uten fargeinlegg, så disse må bestilles utenom.</p>\n<p>Custom fit for hjulbuen til Fisker Ocean</p>\n<p>Alt blir produsert når de bestilles og tar vanligvis 1-5 dager før de blir sendt<span><br></span><br>Laget i PETG (<b>Polyethylene terephthalate glycol)<br><br>Tåler vasking og spriting</b></p>\n<p> </p>\n<p><b> </b></p>",
  "image_count": 11,
  "created_at": "2024-06-30T11:35:25+02:00",
  "updated_at": "2025-07-19T01:36:14+02:00"
}